{
 "courseName": "ISO13485 医療機器品質コース",
 "videos": [],
 "courseQuestions": [],
 "categories": {
  "ISO 13485の基礎と適用範囲": [
   {
    "question": "ISO 13485が主に対象とする分野はどれですか？",
    "options": [
     "自動車部品の製造",
     "医療機器の設計・製造",
     "食品の衛生管理",
     "建設工事の管理"
    ],
    "hint": "規格名に分野が示されています。",
    "correct": 1,
    "explanation": "ISO 13485は医療機器の設計・開発・製造などに関する品質マネジメントシステムの規格です。\n\n出典：ISO 13485（医療機器 品質マネジメントシステム）"
   },
   {
    "question": "ISO 13485のベースとなっている品質マネジメント規格はどれですか？",
    "options": [
     "ISO 9001",
     "ISO 14001",
     "ISO 45001",
     "ISO 27001"
    ],
    "hint": "品質マネジメントの一般規格です。",
    "correct": 0,
    "explanation": "ISO 13485はISO 9001を基礎に、医療機器特有の規制要求を取り込んだ規格です。\n\n出典：ISO 13485（医療機器 品質マネジメントシステム）"
   },
   {
    "question": "医療機器の安全と性能を確保するうえで特に重視される活動はどれですか？",
    "options": [
     "価格競争力",
     "リスク管理",
     "広告宣伝",
     "在庫圧縮"
    ],
    "hint": "患者や使用者の安全に関わる活動です。",
    "correct": 1,
    "explanation": "ISO 13485ではライフサイクル全体を通じたリスクマネジメントが重視されます。\n\n出典：ISO 13485（医療機器 品質マネジメントシステム）"
   },
   {
    "question": "ISO 13485で整備が求められる文書の例として適切なものはどれですか？",
    "options": [
     "品質マニュアル",
     "個人の日記",
     "売上ランキング",
     "顧客の年賀状"
    ],
    "hint": "品質システムを定める文書です。",
    "correct": 0,
    "explanation": "品質マニュアルや手順書など、システムを定め記録する文書の整備が求められます。\n\n出典：ISO 13485（医療機器 品質マネジメントシステム）"
   },
   {
    "question": "「是正処置」の目的として最も適切なものはどれですか？",
    "options": [
     "原因の除去",
     "担当者の処罰",
     "記録の廃棄",
     "検査の省略"
    ],
    "hint": "同じ不適合を繰り返さないために行います。",
    "correct": 0,
    "explanation": "是正処置は不適合の原因を除去し、再発を防ぐために行います。\n\n出典：ISO 13485（医療機器 品質マネジメントシステム）"
   },
   {
    "question": "医療機器のトレーサビリティが意味するものはどれですか？",
    "options": [
     "履歴を追える",
     "製品価格を下げる",
     "在庫を隠す",
     "広告を増やす"
    ],
    "hint": "問題発生時に対象を特定できることが重要です。",
    "correct": 0,
    "explanation": "トレーサビリティは製品の製造・流通の履歴を追跡できることで、回収などに不可欠です。\n\n出典：ISO 13485（医療機器 品質マネジメントシステム）"
   },
   {
    "question": "滅菌医療機器で特に重要となる管理はどれですか？",
    "options": [
     "滅菌の妥当性",
     "製品の色デザイン",
     "広告の頻度",
     "価格の改定"
    ],
    "hint": "滅菌が確実に行われたことを示す必要があります。",
    "correct": 0,
    "explanation": "滅菌工程は結果を全数検証しにくいため、工程の妥当性確認（バリデーション）が重要です。\n\n出典：ISO 13485（医療機器 品質マネジメントシステム）"
   },
   {
    "question": "医療機器の市販後に行う活動として適切なものはどれですか？",
    "options": [
     "苦情処理と監視",
     "設計の中止",
     "宣伝の強化",
     "大規模な値下げ販売"
    ],
    "hint": "市場に出た後の安全確保の活動です。",
    "correct": 0,
    "explanation": "市販後は苦情処理や市販後監視を行い、必要に応じて是正・回収につなげます。\n\n出典：ISO 13485（医療機器 品質マネジメントシステム）"
   }
  ],
  "リスク管理・文書化・是正処置": [
   {
    "question": "リスクマネジメントを行う主な目的はどれですか？",
    "options": [
     "利益の最大化のみ",
     "危害の発生を抑える",
     "書類を増やすため",
     "検査を不要にする"
    ],
    "hint": "患者・使用者への危害を考えます。",
    "correct": 1,
    "explanation": "医療機器のリスクマネジメントは危害の発生確率と重大さを抑えることが目的です。\n\n出典：ISO 13485（医療機器 品質マネジメントシステム）"
   },
   {
    "question": "「予防処置」と「是正処置」の違いとして正しいものはどれですか？",
    "options": [
     "どちらも同じ意味",
     "予防は未然、是正は再発防止",
     "予防は処罰、是正は教育",
     "予防は廃棄、是正は記録"
    ],
    "hint": "問題が起きる前か、起きた後かです。",
    "correct": 1,
    "explanation": "予防処置は起こりうる不適合を未然に防ぎ、是正処置は起きた不適合の再発を防ぎます。\n\n出典：ISO 13485（医療機器 品質マネジメントシステム）"
   },
   {
    "question": "文書管理で求められることとして適切なものはどれですか？",
    "options": [
     "最新版を使えること",
     "旧版を必ず配ること",
     "記録を残さないこと",
     "誰でも改ざんできること"
    ],
    "hint": "古い手順で作業しないための管理です。",
    "correct": 0,
    "explanation": "文書管理では承認・版管理を行い、常に最新の有効な文書を使えるようにします。\n\n出典：ISO 13485（医療機器 品質マネジメントシステム）"
   },
   {
    "question": "内部監査の主な目的として適切なものはどれですか？",
    "options": [
     "担当者を罰する",
     "適合性と有効性の確認",
     "売上を増やす",
     "在庫を減らす"
    ],
    "hint": "システムが守られ機能しているかを確かめます。",
    "correct": 1,
    "explanation": "内部監査は品質システムが要求事項に適合し、有効に機能しているかを確認します。\n\n出典：ISO 13485（医療機器 品質マネジメントシステム）"
   },
   {
    "question": "不適合製品が見つかったときの対応として適切なものはどれですか？",
    "options": [
     "そのまま出荷する",
     "識別して隔離する",
     "記録を消す",
     "値引きして売る"
    ],
    "hint": "誤って使われないようにします。",
    "correct": 1,
    "explanation": "不適合製品は識別・隔離し、誤使用や誤出荷を防いだうえで処置を決めます。\n\n出典：ISO 13485（医療機器 品質マネジメントシステム）"
   },
   {
    "question": "設計・開発の管理で重要となる活動はどれですか？",
    "options": [
     "検証と妥当性確認",
     "宣伝の強化",
     "価格の改定",
     "在庫の圧縮"
    ],
    "hint": "設計が要求を満たすか確かめます。",
    "correct": 0,
    "explanation": "設計の検証（仕様を満たすか）と妥当性確認（実使用で満たすか）が重要です。\n\n出典：ISO 13485（医療機器 品質マネジメントシステム）"
   },
   {
    "question": "教育・訓練を行う主な理由はどれですか？",
    "options": [
     "人件費を増やす",
     "必要な力量を確保する",
     "記録を増やす",
     "残業を減らす"
    ],
    "hint": "業務を適切に行える能力に関わります。",
    "correct": 1,
    "explanation": "製品品質に影響する業務には、必要な力量（能力）を持つ要員の確保が求められます。\n\n出典：ISO 13485（医療機器 品質マネジメントシステム）"
   },
   {
    "question": "供給者（サプライヤ）管理で行うことはどれですか？",
    "options": [
     "評価せず発注する",
     "評価し選定・監視する",
     "価格だけで決める",
     "記録を残さない"
    ],
    "hint": "外部から購入するものも品質に影響します。",
    "correct": 1,
    "explanation": "供給者は評価して選定し、購入品が要求を満たすよう監視・管理します。\n\n出典：ISO 13485（医療機器 品質マネジメントシステム）"
   }
  ]
 }
}